django_waitress/__init__.py
django_waitress/management/__init__.py
django_waitress/management/commands/__init__.py
django_waitress/management/commands/serve.py
django_waitress-0.1.0.dist-info/LICENSE
django_waitress-0.1.0.dist-info/WHEEL
django_waitress-0.1.0.dist-info/METADATA
django_waitress-0.1.0.dist-info/RECORD
